solidgate
