Metadata-Version: 2.1
Name: solidgate-sdk
Version: 0.3.1
Summary: Python API SDK for SolidGate payment gateway
Home-page: https://api-docs.solidgate.com/
Author: SolidGate
Author-email: info@solidgate.com
Classifier: Programming Language :: Python :: 3.7
Classifier: License :: OSI Approved :: MIT License
Classifier: Operating System :: OS Independent
License-File: LICENSE.md
